OPEN_LANE/src/dff_ram_4x72.v
module dff_ram_4x72 (
    input wire clk,
    input wire [1:0]add,
    input wire en_n,
    input wire wr_n,
    input wire [71:0]wdata,

    output reg [71:0]rdata
);
    reg [71:0] mem [0:3];

    always @(posedge clk) begin
        if(!en_n & !wr_n)begin
                mem[add]<= wdata;
        end
        else if(wr_n) begin
            rdata<=mem[add];
        end
end



endmodule

OPEN_LANE/src/dff_ram_8x72.v
module dff_ram_8x72 (
    input wire clk,
    input wire wr_n,
    input wire [2:0] address,
    input wire [71:0] wdata,

    output reg [71:0] rdata
);

    wire [71:0] rdata_inst2;
    wire [71:0] rdata_inst1;
    wire en_1 , en_2;


    assign en_1 = address[2];
    assign en_2 = !(address[2]);


    dff_ram_4x72 instance_0 (
        .clk(clk),
        .en_n(en_1),
        .wr_n(wr_n), 
        .add({address[1:0]}),
        .wdata(wdata),
        .rdata(rdata_inst1)
    );

    dff_ram_4x72 instance_1 (
        .clk(clk),
        .en_n(en_2),
        .wr_n(wr_n), 
        .add({address[1:0]}),
        .wdata(wdata),
        .rdata(rdata_inst2)
    );

    always @* begin
        if (address[2] == 0) begin
            rdata = rdata_inst1;
        end else begin
            rdata = rdata_inst2;
        end
    end

endmodule

OPEN_LANE/tb/dff_ram_8x72_tb.v
`timescale 1ns/1ns
module tb_dff_ram_8x72;

    reg clk;
    reg wr_n;
    reg [2:0] address;
    reg [71:0] wdata;
    wire [71:0] rdata;

    // Instantiate the module under test
    dff_ram_8x72 dut (
        .clk(clk),
        .wr_n(wr_n),
        .address(address),
        .wdata(wdata),
        .rdata(rdata)
    );

    // Test stimuli
    initial begin
        clk = 0;
        wr_n = 0;
        
        // Write data to specific addresses
        #10;
        address = 0;
        wr_n = 0;
        // Initialize data
        wdata = 72'd1;

        #10;
        address = 1;
        wr_n = 0;
        wdata = 72'd2;

        #10;
        address = 2;
        wr_n = 0;
        // Initialize data
        wdata = 72'd3;

        #10;
        address = 3;
        wr_n = 0;
        wdata = 72'd4;

        #10;
        address = 4;
        wr_n = 0;
        // Initialize data
        wdata = 72'd5;

        #10;
        address = 5;
        wr_n = 0;
        wdata = 72'd6;

        #10;
        address = 6;
        wr_n = 0;
        // Initialize data
        wdata = 72'd7;

        #10;
        address = 7;
        wr_n = 0;
        wdata = 72'd8;

        // Read data from written addresses
        #10;
        address = 0;
        wr_n = 1;

        #10; 
        address = 1;
        wr_n = 1;

        #10;
        address = 2;
        wr_n = 1;

        #10; 
        address = 3;
        wr_n = 1;

        #10;
        address = 4;
        wr_n = 1;

        #10; 
        address = 5;
        wr_n = 1;

        #10;
        address = 6;
        wr_n = 1;

        #10; 
        address = 7;
        wr_n = 1;
        #20;

        $finish;
    end

    initial begin
       $dumpfile("temp/dff8.vcd");
       $dumpvars(0,tb_dff_ram_8x72);
    end

    always #5 clk = ~clk;

endmodule

OPEN_LANE/temp/dff8.vcd
$date
	Thu Feb 15 17:34:03 2024
$end
$version
	Icarus Verilog
$end
$timescale
	1ns
$end
$scope module tb_dff_ram_8x72 $end
$var wire 72 ! rdata [71:0] $end
$var reg 3 " address [2:0] $end
$var reg 1 # clk $end
$var reg 72 $ wdata [71:0] $end
$var reg 1 % wr_n $end
$scope module dut $end
$var wire 3 & address [2:0] $end
$var wire 1 # clk $end
$var wire 72 ' wdata [71:0] $end
$var wire 1 % wr_n $end
$var wire 72 ( rdata_inst2 [71:0] $end
$var wire 72 ) rdata_inst1 [71:0] $end
$var wire 1 * en_2 $end
$var wire 1 + en_1 $end
$var reg 72 , rdata [71:0] $end
$scope module instance_0 $end
$var wire 2 - add [1:0] $end
$var wire 1 # clk $end
$var wire 1 + en_n $end
$var wire 72 . wdata [71:0] $end
$var wire 1 % wr_n $end
$var reg 72 / rdata [71:0] $end
$upscope $end
$scope module instance_1 $end
$var wire 2 0 add [1:0] $end
$var wire 1 # clk $end
$var wire 1 * en_n $end
$var wire 72 1 wdata [71:0] $end
$var wire 1 % wr_n $end
$var reg 72 2 rdata [71:0] $end
$upscope $end
$upscope $end
$upscope $end
$enddefinitions $end
#0
$dumpvars
bx 2
bx 1
bx 0
bx /
bx .
bx -
bx ,
x+
x*
bx )
bx (
bx '
bx &
0%
bx $
0#
bx "
bx !
$end
#5
1#
#10
0+
1*
b0 -
b0 0
0#
b1 $
b1 '
b1 .
b1 1
b0 "
b0 &
#15
1#
#20
b1 -
b1 0
0#
b10 $
b10 '
b10 .
b10 1
b1 "
b1 &
#25
1#
#30
b10 -
b10 0
0#
b11 $
b11 '
b11 .
b11 1
b10 "
b10 &
#35
1#
#40
b11 -
b11 0
0#
b100 $
b100 '
b100 .
b100 1
b11 "
b11 &
#45
1#
#50
1+
0*
b0 -
b0 0
0#
b101 $
b101 '
b101 .
b101 1
b100 "
b100 &
#55
1#
#60
b1 -
b1 0
0#
b110 $
b110 '
b110 .
b110 1
b101 "
b101 &
#65
1#
#70
b10 -
b10 0
0#
b111 $
b111 '
b111 .
b111 1
b110 "
b110 &
#75
1#
#80
b11 -
b11 0
0#
b1000 $
b1000 '
b1000 .
b1000 1
b111 "
b111 &
#85
1#
#90
0+
1*
b0 -
b0 0
0#
1%
b0 "
b0 &
#95
b1 !
b1 ,
b101 (
b101 2
b1 )
b1 /
1#
#100
b1 -
b1 0
0#
b1 "
b1 &
#105
b10 !
b10 ,
b10 )
b10 /
b110 (
b110 2
1#
#110
b10 -
b10 0
0#
b10 "
b10 &
#115
b11 !
b11 ,
b111 (
b111 2
b11 )
b11 /
1#
#120
b11 -
b11 0
0#
b11 "
b11 &
#125
b100 !
b100 ,
b100 )
b100 /
b1000 (
b1000 2
1#
#130
b1000 !
b1000 ,
1+
0*
b0 -
b0 0
0#
b100 "
b100 &
#135
b101 !
b101 ,
b101 (
b101 2
b1 )
b1 /
1#
#140
b1 -
b1 0
0#
b101 "
b101 &
#145
b110 !
b110 ,
b10 )
b10 /
b110 (
b110 2
1#
#150
b10 -
b10 0
0#
b110 "
b110 &
#155
b111 !
b111 ,
b111 (
b111 2
b11 )
b11 /
1#
#160
b11 -
b11 0
0#
b111 "
b111 &
#165
b1000 !
b1000 ,
b100 )
b100 /
b1000 (
b1000 2
1#
